ddd/__init__.py
ddd/application/__init__.py
ddd/application/command.py
ddd/application/command_handler.py
ddd/domain/__init__.py
ddd/domain/aggregate_root.py
ddd/domain/domain_event.py
ddd/domain/entity.py
ddd/domain/value_object.py
ddd/domain/value/__init__.py
ddd/domain/value/identity.py
dddx-0.1.1.dist-info/licenses/LICENSE
dddx-0.1.1.dist-info/METADATA
dddx-0.1.1.dist-info/WHEEL
dddx-0.1.1.dist-info/top_level.txt
dddx-0.1.1.dist-info/RECORD
